{"topicSections":[{"identifiers":["doc:\/\/com.proglove.Mark2SDK\/documentation\/ConnectSDK\/initate-connection"],"title":"Essentials"},{"title":"Models","identifiers":["doc:\/\/com.proglove.Mark2SDK\/documentation\/ConnectSDK\/PGDeviceInformation","doc:\/\/com.proglove.Mark2SDK\/documentation\/ConnectSDK\/PGScreenData"]},{"title":"Classes","identifiers":["doc:\/\/com.proglove.Mark2SDK\/documentation\/ConnectSDK\/PGCaptureImageRequest","doc:\/\/com.proglove.Mark2SDK\/documentation\/ConnectSDK\/PGCentralManager","doc:\/\/com.proglove.Mark2SDK\/documentation\/ConnectSDK\/PGCommand","doc:\/\/com.proglove.Mark2SDK\/documentation\/ConnectSDK\/PGCommandParams","doc:\/\/com.proglove.Mark2SDK\/documentation\/ConnectSDK\/PGConfigurationProfile","doc:\/\/com.proglove.Mark2SDK\/documentation\/ConnectSDK\/PGDeviceInformationRequest","doc:\/\/com.proglove.Mark2SDK\/documentation\/ConnectSDK\/PGFeedbackRequest","doc:\/\/com.proglove.Mark2SDK\/documentation\/ConnectSDK\/PGImage","doc:\/\/com.proglove.Mark2SDK\/documentation\/ConnectSDK\/PGLogging","doc:\/\/com.proglove.Mark2SDK\/documentation\/ConnectSDK\/PGManager","doc:\/\/com.proglove.Mark2SDK\/documentation\/ConnectSDK\/PGMockPeripheral","doc:\/\/com.proglove.Mark2SDK\/documentation\/ConnectSDK\/PGPairingQR","doc:\/\/com.proglove.Mark2SDK\/documentation\/ConnectSDK\/PGPairingQRGeneratorOptions","doc:\/\/com.proglove.Mark2SDK\/documentation\/ConnectSDK\/PGPeripheral","doc:\/\/com.proglove.Mark2SDK\/documentation\/ConnectSDK\/PGScannedBarcodeResult","doc:\/\/com.proglove.Mark2SDK\/documentation\/ConnectSDK\/PGSetDisplayOrientationRequest","doc:\/\/com.proglove.Mark2SDK\/documentation\/ConnectSDK\/PGTemplateField"]},{"identifiers":["doc:\/\/com.proglove.Mark2SDK\/documentation\/ConnectSDK\/PGCentralManagerDelegate","doc:\/\/com.proglove.Mark2SDK\/documentation\/ConnectSDK\/PGCloudConnectionDelegate","doc:\/\/com.proglove.Mark2SDK\/documentation\/ConnectSDK\/PGConfigurationManager","doc:\/\/com.proglove.Mark2SDK\/documentation\/ConnectSDK\/PGConfigurationManagerDelegate","doc:\/\/com.proglove.Mark2SDK\/documentation\/ConnectSDK\/PGDisplayManager","doc:\/\/com.proglove.Mark2SDK\/documentation\/ConnectSDK\/PGFeedbackManager","doc:\/\/com.proglove.Mark2SDK\/documentation\/ConnectSDK\/PGFirmwareUpdateManager","doc:\/\/com.proglove.Mark2SDK\/documentation\/ConnectSDK\/PGFirmwareUpdateManagerDelegate","doc:\/\/com.proglove.Mark2SDK\/documentation\/ConnectSDK\/PGImageManager","doc:\/\/com.proglove.Mark2SDK\/documentation\/ConnectSDK\/PGLoggingDelegate","doc:\/\/com.proglove.Mark2SDK\/documentation\/ConnectSDK\/PGManagerDelegate","doc:\/\/com.proglove.Mark2SDK\/documentation\/ConnectSDK\/PGPeripheralDelegate"],"title":"Protocols"},{"title":"Variables","identifiers":["doc:\/\/com.proglove.Mark2SDK\/documentation\/ConnectSDK\/PGCloudBulkErrorDomain","doc:\/\/com.proglove.Mark2SDK\/documentation\/ConnectSDK\/PGCloudErrorDomain","doc:\/\/com.proglove.Mark2SDK\/documentation\/ConnectSDK\/PGCloudFleetErrorDomain","doc:\/\/com.proglove.Mark2SDK\/documentation\/ConnectSDK\/PGConfigurationErrorDomain","doc:\/\/com.proglove.Mark2SDK\/documentation\/ConnectSDK\/PGDeviceLockErrorDomain","doc:\/\/com.proglove.Mark2SDK\/documentation\/ConnectSDK\/PGDisplayApiErrorDomain","doc:\/\/com.proglove.Mark2SDK\/documentation\/ConnectSDK\/PGFeedbackApiErrorDomain","doc:\/\/com.proglove.Mark2SDK\/documentation\/ConnectSDK\/PGFirmwareUpdateErrorDomain","doc:\/\/com.proglove.Mark2SDK\/documentation\/ConnectSDK\/PGPairingQRGeneratorErrorDomain","doc:\/\/com.proglove.Mark2SDK\/documentation\/ConnectSDK\/PGPeripheralErrorCentralHasRetriedConnectingKey","doc:\/\/com.proglove.Mark2SDK\/documentation\/ConnectSDK\/PGPeripheralErrorDomain","doc:\/\/com.proglove.Mark2SDK\/documentation\/ConnectSDK\/PGPeripheralErrorIncompatibleModelNumberKey","doc:\/\/com.proglove.Mark2SDK\/documentation\/ConnectSDK\/PGPeripheralErrorServiceKey","doc:\/\/com.proglove.Mark2SDK\/documentation\/ConnectSDK\/PGURLErrorDomain","doc:\/\/com.proglove.Mark2SDK\/documentation\/ConnectSDK\/PGWearableApiErrorDomain"]},{"title":"Enumerations","identifiers":["doc:\/\/com.proglove.Mark2SDK\/documentation\/ConnectSDK\/PGButtonTriggerEventType","doc:\/\/com.proglove.Mark2SDK\/documentation\/ConnectSDK\/PGCloudConnectionStatus","doc:\/\/com.proglove.Mark2SDK\/documentation\/ConnectSDK\/PGConfigurationApiError","doc:\/\/com.proglove.Mark2SDK\/documentation\/ConnectSDK\/PGDeviceLockError","doc:\/\/com.proglove.Mark2SDK\/documentation\/ConnectSDK\/PGDisplayApiError","doc:\/\/com.proglove.Mark2SDK\/documentation\/ConnectSDK\/PGFeedbackApiError","doc:\/\/com.proglove.Mark2SDK\/documentation\/ConnectSDK\/PGImageResolution","doc:\/\/com.proglove.Mark2SDK\/documentation\/ConnectSDK\/PGLogFlag","doc:\/\/com.proglove.Mark2SDK\/documentation\/ConnectSDK\/PGLogLevel","doc:\/\/com.proglove.Mark2SDK\/documentation\/ConnectSDK\/PGManagerState","doc:\/\/com.proglove.Mark2SDK\/documentation\/ConnectSDK\/PGOrientation","doc:\/\/com.proglove.Mark2SDK\/documentation\/ConnectSDK\/PGPairingQRGeneratorApiError","doc:\/\/com.proglove.Mark2SDK\/documentation\/ConnectSDK\/PGPairingQRGeneratorErrorCorrectionLevel","doc:\/\/com.proglove.Mark2SDK\/documentation\/ConnectSDK\/PGPeripheralError","doc:\/\/com.proglove.Mark2SDK\/documentation\/ConnectSDK\/PGPeripheralLockState","doc:\/\/com.proglove.Mark2SDK\/documentation\/ConnectSDK\/PGPeripheralState","doc:\/\/com.proglove.Mark2SDK\/documentation\/ConnectSDK\/PGPredefinedFeedback","doc:\/\/com.proglove.Mark2SDK\/documentation\/ConnectSDK\/PGRefreshType","doc:\/\/com.proglove.Mark2SDK\/documentation\/ConnectSDK\/PGWearableApiError"]}],"variants":[{"traits":[{"interfaceLanguage":"swift"}],"paths":["\/documentation\/connectsdk"]},{"traits":[{"interfaceLanguage":"occ"}],"paths":["\/documentation\/connectsdk"]}],"identifier":{"interfaceLanguage":"swift","url":"doc:\/\/com.proglove.Mark2SDK\/documentation\/ConnectSDK"},"schemaVersion":{"major":0,"patch":0,"minor":3},"metadata":{"title":"ConnectSDK","externalID":"ConnectSDK","roleHeading":"Framework","modules":[{"name":"ConnectSDK"}],"symbolKind":"module","role":"collection"},"abstract":[{"type":"text","text":"The "},{"type":"strong","inlineContent":[{"type":"text","text":"ProGlove ConnectSDK"}]},{"type":"text","text":" is a software development kit that enables integration between your iOS apps and the ProGlove system."}],"primaryContentSections":[{"kind":"content","content":[{"text":"Overview","anchor":"Overview","level":2,"type":"heading"},{"type":"paragraph","inlineContent":[{"text":"The ","type":"text"},{"type":"strong","inlineContent":[{"text":"ConnectSDK","type":"text"}]},{"text":" provides a set of APIs that allow your apps to scan for ProGlove devices, connect to them, and interact with them.","type":"text"}]},{"type":"paragraph","inlineContent":[{"type":"image","identifier":"introduction-graph.png"}]}]}],"sections":[],"kind":"symbol","hierarchy":{"paths":[[]]},"references":{"doc://com.proglove.Mark2SDK/documentation/ConnectSDK/PGFeedbackManager":{"abstract":[{"type":"text","text":"Protocol contains all the feedback related methods."}],"url":"\/documentation\/connectsdk\/pgfeedbackmanager","type":"topic","kind":"symbol","role":"symbol","fragments":[{"text":"protocol","kind":"keyword"},{"text":" ","kind":"text"},{"kind":"identifier","text":"PGFeedbackManager"}],"identifier":"doc:\/\/com.proglove.Mark2SDK\/documentation\/ConnectSDK\/PGFeedbackManager","navigatorTitle":[{"kind":"identifier","text":"PGFeedbackManager"}],"title":"PGFeedbackManager"},"doc://com.proglove.Mark2SDK/documentation/ConnectSDK/PGCloudBulkErrorDomain":{"url":"\/documentation\/connectsdk\/pgcloudbulkerrordomain","identifier":"doc:\/\/com.proglove.Mark2SDK\/documentation\/ConnectSDK\/PGCloudBulkErrorDomain","title":"PGCloudBulkErrorDomain","kind":"symbol","fragments":[{"text":"let","kind":"keyword"},{"kind":"text","text":" "},{"text":"PGCloudBulkErrorDomain","kind":"identifier"},{"text":": ","kind":"text"},{"kind":"typeIdentifier","text":"String","preciseIdentifier":"s:SS"}],"abstract":[{"text":"The Bulk Provisioning Error Domain","type":"text"}],"type":"topic","role":"symbol","navigatorTitle":[{"kind":"identifier","text":"PGCloudBulkErrorDomain"}]},"doc://com.proglove.Mark2SDK/documentation/ConnectSDK/PGFeedbackApiErrorDomain":{"navigatorTitle":[{"text":"PGFeedbackApiErrorDomain","kind":"identifier"}],"role":"symbol","abstract":[{"text":"The scanner feedback api error domain.","type":"text"}],"identifier":"doc:\/\/com.proglove.Mark2SDK\/documentation\/ConnectSDK\/PGFeedbackApiErrorDomain","url":"\/documentation\/connectsdk\/pgfeedbackapierrordomain","fragments":[{"kind":"keyword","text":"let"},{"kind":"text","text":" "},{"kind":"identifier","text":"PGFeedbackApiErrorDomain"},{"text":": ","kind":"text"},{"text":"String","kind":"typeIdentifier","preciseIdentifier":"s:SS"}],"title":"PGFeedbackApiErrorDomain","kind":"symbol","type":"topic"},"doc://com.proglove.Mark2SDK/documentation/ConnectSDK/PGPeripheralErrorIncompatibleModelNumberKey":{"navigatorTitle":[{"text":"PGPeripheralErrorIncompatibleModelNumberKey","kind":"identifier"}],"role":"symbol","abstract":[{"text":"The incompatible model number NSString that was discovered for this device","type":"text"}],"identifier":"doc:\/\/com.proglove.Mark2SDK\/documentation\/ConnectSDK\/PGPeripheralErrorIncompatibleModelNumberKey","url":"\/documentation\/connectsdk\/pgperipheralerrorincompatiblemodelnumberkey","fragments":[{"kind":"keyword","text":"let"},{"text":" ","kind":"text"},{"kind":"identifier","text":"PGPeripheralErrorIncompatibleModelNumberKey"},{"kind":"text","text":": "},{"text":"String","kind":"typeIdentifier","preciseIdentifier":"s:SS"}],"kind":"symbol","title":"PGPeripheralErrorIncompatibleModelNumberKey","type":"topic"},"doc://com.proglove.Mark2SDK/documentation/ConnectSDK/PGDisplayApiError":{"title":"PGDisplayApiError","url":"\/documentation\/connectsdk\/pgdisplayapierror","role":"symbol","navigatorTitle":[{"text":"PGDisplayApiError","kind":"identifier"}],"identifier":"doc:\/\/com.proglove.Mark2SDK\/documentation\/ConnectSDK\/PGDisplayApiError","abstract":[{"text":"PG Display API error codes.","type":"text"}],"fragments":[{"kind":"keyword","text":"enum"},{"kind":"text","text":" "},{"kind":"identifier","text":"PGDisplayApiError"}],"kind":"symbol","type":"topic"},"doc://com.proglove.Mark2SDK/documentation/ConnectSDK/PGURLErrorDomain":{"type":"topic","identifier":"doc:\/\/com.proglove.Mark2SDK\/documentation\/ConnectSDK\/PGURLErrorDomain","kind":"symbol","fragments":[{"kind":"keyword","text":"let"},{"kind":"text","text":" "},{"kind":"identifier","text":"PGURLErrorDomain"},{"kind":"text","text":": "},{"preciseIdentifier":"s:SS","kind":"typeIdentifier","text":"String"}],"navigatorTitle":[{"text":"PGURLErrorDomain","kind":"identifier"}],"url":"\/documentation\/connectsdk\/pgurlerrordomain","title":"PGURLErrorDomain","abstract":[{"text":"The URL Request Error Domain","type":"text"}],"role":"symbol"},"doc://com.proglove.Mark2SDK/documentation/ConnectSDK/PGConfigurationManagerDelegate":{"abstract":[],"navigatorTitle":[{"text":"PGConfigurationManagerDelegate","kind":"identifier"}],"type":"topic","identifier":"doc:\/\/com.proglove.Mark2SDK\/documentation\/ConnectSDK\/PGConfigurationManagerDelegate","fragments":[{"text":"protocol","kind":"keyword"},{"kind":"text","text":" "},{"text":"PGConfigurationManagerDelegate","kind":"identifier"}],"title":"PGConfigurationManagerDelegate","url":"\/documentation\/connectsdk\/pgconfigurationmanagerdelegate","role":"symbol","kind":"symbol"},"doc://com.proglove.Mark2SDK/documentation/ConnectSDK/PGPairingQRGeneratorApiError":{"role":"symbol","fragments":[{"kind":"keyword","text":"enum"},{"kind":"text","text":" "},{"text":"PGPairingQRGeneratorApiError","kind":"identifier"}],"url":"\/documentation\/connectsdk\/pgpairingqrgeneratorapierror","kind":"symbol","title":"PGPairingQRGeneratorApiError","navigatorTitle":[{"kind":"identifier","text":"PGPairingQRGeneratorApiError"}],"type":"topic","abstract":[{"text":"PG pairing barcode generator error codes","type":"text"}],"identifier":"doc:\/\/com.proglove.Mark2SDK\/documentation\/ConnectSDK\/PGPairingQRGeneratorApiError"},"doc://com.proglove.Mark2SDK/documentation/ConnectSDK/PGButtonTriggerEventType":{"kind":"symbol","identifier":"doc:\/\/com.proglove.Mark2SDK\/documentation\/ConnectSDK\/PGButtonTriggerEventType","type":"topic","fragments":[{"kind":"keyword","text":"enum"},{"kind":"text","text":" "},{"kind":"identifier","text":"PGButtonTriggerEventType"}],"navigatorTitle":[{"kind":"identifier","text":"PGButtonTriggerEventType"}],"url":"\/documentation\/connectsdk\/pgbuttontriggereventtype","title":"PGButtonTriggerEventType","abstract":[{"text":"The button trigger event types","type":"text"}],"role":"symbol"},"doc://com.proglove.Mark2SDK/documentation/ConnectSDK/PGFirmwareUpdateManager":{"kind":"symbol","type":"topic","identifier":"doc:\/\/com.proglove.Mark2SDK\/documentation\/ConnectSDK\/PGFirmwareUpdateManager","fragments":[{"kind":"keyword","text":"protocol"},{"kind":"text","text":" "},{"kind":"identifier","text":"PGFirmwareUpdateManager"}],"navigatorTitle":[{"text":"PGFirmwareUpdateManager","kind":"identifier"}],"url":"\/documentation\/connectsdk\/pgfirmwareupdatemanager","title":"PGFirmwareUpdateManager","abstract":[{"text":"The protocol for the PGFirmwareUpdateManager.","type":"text"}],"role":"symbol"},"doc://com.proglove.Mark2SDK/documentation/ConnectSDK/PGPeripheralErrorServiceKey":{"kind":"symbol","identifier":"doc:\/\/com.proglove.Mark2SDK\/documentation\/ConnectSDK\/PGPeripheralErrorServiceKey","type":"topic","fragments":[{"kind":"keyword","text":"let"},{"kind":"text","text":" "},{"kind":"identifier","text":"PGPeripheralErrorServiceKey"},{"kind":"text","text":": "},{"text":"String","kind":"typeIdentifier","preciseIdentifier":"s:SS"}],"navigatorTitle":[{"kind":"identifier","text":"PGPeripheralErrorServiceKey"}],"url":"\/documentation\/connectsdk\/pgperipheralerrorservicekey","title":"PGPeripheralErrorServiceKey","abstract":[{"text":"The UUID string of the service the error occurred on","type":"text"}],"role":"symbol"},"doc://com.proglove.Mark2SDK/documentation/ConnectSDK/PGCloudConnectionStatus":{"fragments":[{"kind":"keyword","text":"enum"},{"text":" ","kind":"text"},{"text":"PGCloudConnectionStatus","kind":"identifier"}],"abstract":[{"type":"text","text":"Connection status to Insight portal"}],"identifier":"doc:\/\/com.proglove.Mark2SDK\/documentation\/ConnectSDK\/PGCloudConnectionStatus","url":"\/documentation\/connectsdk\/pgcloudconnectionstatus","role":"symbol","kind":"symbol","type":"topic","title":"PGCloudConnectionStatus","navigatorTitle":[{"kind":"identifier","text":"PGCloudConnectionStatus"}]},"doc://com.proglove.Mark2SDK/documentation/ConnectSDK/PGManagerDelegate":{"kind":"symbol","type":"topic","identifier":"doc:\/\/com.proglove.Mark2SDK\/documentation\/ConnectSDK\/PGManagerDelegate","fragments":[{"text":"protocol","kind":"keyword"},{"kind":"text","text":" "},{"text":"PGManagerDelegate","kind":"identifier"}],"navigatorTitle":[{"kind":"identifier","text":"PGManagerDelegate"}],"url":"\/documentation\/connectsdk\/pgmanagerdelegate","title":"PGManagerDelegate","abstract":[{"text":"The delegate of a {@link PGManager} object must adopt the ","type":"text"},{"text":"PGManagerDelegate","type":"text"},{"text":" protocol. The","type":"text"},{"text":" ","type":"text"},{"type":"text","text":"single required method indicates the availability of the manager."}],"role":"symbol"},"doc://com.proglove.Mark2SDK/documentation/ConnectSDK/PGWearableApiError":{"abstract":[{"text":"PG Wearable API error codes","type":"text"}],"title":"PGWearableApiError","navigatorTitle":[{"text":"PGWearableApiError","kind":"identifier"}],"role":"symbol","identifier":"doc:\/\/com.proglove.Mark2SDK\/documentation\/ConnectSDK\/PGWearableApiError","url":"\/documentation\/connectsdk\/pgwearableapierror","type":"topic","kind":"symbol","fragments":[{"text":"enum","kind":"keyword"},{"text":" ","kind":"text"},{"text":"PGWearableApiError","kind":"identifier"}]},"doc://com.proglove.Mark2SDK/documentation/ConnectSDK/PGCentralManager":{"type":"topic","identifier":"doc:\/\/com.proglove.Mark2SDK\/documentation\/ConnectSDK\/PGCentralManager","kind":"symbol","role":"symbol","title":"PGCentralManager","abstract":[{"type":"text","text":"PGCentralManager"}],"url":"\/documentation\/connectsdk\/pgcentralmanager","navigatorTitle":[{"kind":"identifier","text":"PGCentralManager"}],"fragments":[{"text":"class","kind":"keyword"},{"kind":"text","text":" "},{"text":"PGCentralManager","kind":"identifier"}]},"doc://com.proglove.Mark2SDK/documentation/ConnectSDK/PGFirmwareUpdateErrorDomain":{"kind":"symbol","type":"topic","identifier":"doc:\/\/com.proglove.Mark2SDK\/documentation\/ConnectSDK\/PGFirmwareUpdateErrorDomain","fragments":[{"kind":"keyword","text":"let"},{"text":" ","kind":"text"},{"text":"PGFirmwareUpdateErrorDomain","kind":"identifier"},{"kind":"text","text":": "},{"text":"String","preciseIdentifier":"s:SS","kind":"typeIdentifier"}],"navigatorTitle":[{"text":"PGFirmwareUpdateErrorDomain","kind":"identifier"}],"url":"\/documentation\/connectsdk\/pgfirmwareupdateerrordomain","title":"PGFirmwareUpdateErrorDomain","abstract":[{"text":"Firmware Update Error Domain","type":"text"}],"role":"symbol"},"doc://com.proglove.Mark2SDK/documentation/ConnectSDK/PGConfigurationManager":{"identifier":"doc:\/\/com.proglove.Mark2SDK\/documentation\/ConnectSDK\/PGConfigurationManager","type":"topic","role":"symbol","fragments":[{"text":"protocol","kind":"keyword"},{"text":" ","kind":"text"},{"text":"PGConfigurationManager","kind":"identifier"}],"kind":"symbol","navigatorTitle":[{"text":"PGConfigurationManager","kind":"identifier"}],"abstract":[],"url":"\/documentation\/connectsdk\/pgconfigurationmanager","title":"PGConfigurationManager"},"doc://com.proglove.Mark2SDK/documentation/ConnectSDK/PGPairingQRGeneratorErrorDomain":{"kind":"symbol","type":"topic","identifier":"doc:\/\/com.proglove.Mark2SDK\/documentation\/ConnectSDK\/PGPairingQRGeneratorErrorDomain","fragments":[{"kind":"keyword","text":"let"},{"text":" ","kind":"text"},{"text":"PGPairingQRGeneratorErrorDomain","kind":"identifier"},{"kind":"text","text":": "},{"text":"String","kind":"typeIdentifier","preciseIdentifier":"s:SS"}],"navigatorTitle":[{"kind":"identifier","text":"PGPairingQRGeneratorErrorDomain"}],"url":"\/documentation\/connectsdk\/pgpairingqrgeneratorerrordomain","title":"PGPairingQRGeneratorErrorDomain","abstract":[{"type":"text","text":"The ParingQRGenerator Error Domain"}],"role":"symbol"},"doc://com.proglove.Mark2SDK/documentation/ConnectSDK/PGOrientation":{"abstract":[{"type":"text","text":"Definition of the valid display orientations."}],"role":"symbol","identifier":"doc:\/\/com.proglove.Mark2SDK\/documentation\/ConnectSDK\/PGOrientation","navigatorTitle":[{"kind":"identifier","text":"PGOrientation"}],"title":"PGOrientation","url":"\/documentation\/connectsdk\/pgorientation","fragments":[{"text":"enum","kind":"keyword"},{"text":" ","kind":"text"},{"kind":"identifier","text":"PGOrientation"}],"type":"topic","kind":"symbol"},"doc://com.proglove.Mark2SDK/documentation/ConnectSDK/PGDeviceInformation":{"identifier":"doc:\/\/com.proglove.Mark2SDK\/documentation\/ConnectSDK\/PGDeviceInformation","fragments":[{"kind":"keyword","text":"class"},{"kind":"text","text":" "},{"kind":"identifier","text":"PGDeviceInformation"}],"abstract":[{"text":"Model representing device information","type":"text"}],"url":"\/documentation\/connectsdk\/pgdeviceinformation","navigatorTitle":[{"kind":"identifier","text":"PGDeviceInformation"}],"type":"topic","role":"symbol","title":"PGDeviceInformation","kind":"symbol"},"doc://com.proglove.Mark2SDK/documentation/ConnectSDK/PGPredefinedFeedback":{"kind":"symbol","identifier":"doc:\/\/com.proglove.Mark2SDK\/documentation\/ConnectSDK\/PGPredefinedFeedback","type":"topic","fragments":[{"kind":"keyword","text":"enum"},{"kind":"text","text":" "},{"kind":"identifier","text":"PGPredefinedFeedback"}],"navigatorTitle":[{"kind":"identifier","text":"PGPredefinedFeedback"}],"url":"\/documentation\/connectsdk\/pgpredefinedfeedback","title":"PGPredefinedFeedback","abstract":[{"text":"Feedback enum","type":"text"}],"role":"symbol"},"doc://com.proglove.Mark2SDK/documentation/ConnectSDK/PGCloudFleetErrorDomain":{"kind":"symbol","type":"topic","identifier":"doc:\/\/com.proglove.Mark2SDK\/documentation\/ConnectSDK\/PGCloudFleetErrorDomain","fragments":[{"text":"let","kind":"keyword"},{"kind":"text","text":" "},{"kind":"identifier","text":"PGCloudFleetErrorDomain"},{"kind":"text","text":": "},{"kind":"typeIdentifier","preciseIdentifier":"s:SS","text":"String"}],"navigatorTitle":[{"text":"PGCloudFleetErrorDomain","kind":"identifier"}],"url":"\/documentation\/connectsdk\/pgcloudfleeterrordomain","title":"PGCloudFleetErrorDomain","abstract":[{"text":"The Fleet Provisioning Error Domain","type":"text"}],"role":"symbol"},"doc://com.proglove.Mark2SDK/documentation/ConnectSDK/PGFeedbackRequest":{"type":"topic","identifier":"doc:\/\/com.proglove.Mark2SDK\/documentation\/ConnectSDK\/PGFeedbackRequest","kind":"symbol","fragments":[{"kind":"keyword","text":"class"},{"kind":"text","text":" "},{"kind":"identifier","text":"PGFeedbackRequest"}],"navigatorTitle":[{"kind":"identifier","text":"PGFeedbackRequest"}],"url":"\/documentation\/connectsdk\/pgfeedbackrequest","title":"PGFeedbackRequest","abstract":[{"text":"Model representing PGFeedback Request","type":"text"}],"role":"symbol"},"doc://com.proglove.Mark2SDK/documentation/ConnectSDK/PGDeviceLockError":{"abstract":[{"text":"Scanner lock\/unlock error codes","type":"text"}],"identifier":"doc:\/\/com.proglove.Mark2SDK\/documentation\/ConnectSDK\/PGDeviceLockError","type":"topic","role":"symbol","kind":"symbol","fragments":[{"text":"enum","kind":"keyword"},{"kind":"text","text":" "},{"text":"PGDeviceLockError","kind":"identifier"}],"navigatorTitle":[{"text":"PGDeviceLockError","kind":"identifier"}],"title":"PGDeviceLockError","url":"\/documentation\/connectsdk\/pgdevicelockerror"},"doc://com.proglove.Mark2SDK/documentation/ConnectSDK/PGPairingQR":{"identifier":"doc:\/\/com.proglove.Mark2SDK\/documentation\/ConnectSDK\/PGPairingQR","abstract":[],"navigatorTitle":[{"text":"PGPairingQR","kind":"identifier"}],"type":"topic","url":"\/documentation\/connectsdk\/pgpairingqr","title":"PGPairingQR","role":"symbol","kind":"symbol","fragments":[{"text":"class","kind":"keyword"},{"text":" ","kind":"text"},{"kind":"identifier","text":"PGPairingQR"}]},"doc://com.proglove.Mark2SDK/documentation/ConnectSDK/PGLoggingDelegate":{"identifier":"doc:\/\/com.proglove.Mark2SDK\/documentation\/ConnectSDK\/PGLoggingDelegate","url":"\/documentation\/connectsdk\/pgloggingdelegate","abstract":[{"type":"text","text":"The logging class delegate protocol"}],"kind":"symbol","role":"symbol","fragments":[{"text":"protocol","kind":"keyword"},{"kind":"text","text":" "},{"text":"PGLoggingDelegate","kind":"identifier"}],"navigatorTitle":[{"text":"PGLoggingDelegate","kind":"identifier"}],"type":"topic","title":"PGLoggingDelegate"},"doc://com.proglove.Mark2SDK/documentation/ConnectSDK/PGFirmwareUpdateManagerDelegate":{"kind":"symbol","type":"topic","identifier":"doc:\/\/com.proglove.Mark2SDK\/documentation\/ConnectSDK\/PGFirmwareUpdateManagerDelegate","fragments":[{"text":"protocol","kind":"keyword"},{"kind":"text","text":" "},{"kind":"identifier","text":"PGFirmwareUpdateManagerDelegate"}],"navigatorTitle":[{"text":"PGFirmwareUpdateManagerDelegate","kind":"identifier"}],"url":"\/documentation\/connectsdk\/pgfirmwareupdatemanagerdelegate","title":"PGFirmwareUpdateManagerDelegate","abstract":[{"text":"PGFirmwareUpdateManagerDelegate","type":"text"},{"type":"text","text":" "},{"type":"text","text":"The delegate protocol for the PGFirmwareUpdateManager. The delegate must adopt the PGFirmwareUpdateManagerDelegate protocol."},{"text":" ","type":"text"},{"text":"The methods will provide the firmware update state information.","type":"text"}],"role":"symbol"},"doc://com.proglove.Mark2SDK/documentation/ConnectSDK/PGCommand":{"abstract":[{"text":"A PGCommand is used to send a command to a connected device through Connect SDK.","type":"text"}],"title":"PGCommand","url":"\/documentation\/connectsdk\/pgcommand","role":"symbol","fragments":[{"text":"class","kind":"keyword"},{"text":" ","kind":"text"},{"text":"PGCommand","kind":"identifier"}],"identifier":"doc:\/\/com.proglove.Mark2SDK\/documentation\/ConnectSDK\/PGCommand","navigatorTitle":[{"kind":"identifier","text":"PGCommand"}],"kind":"symbol","type":"topic"},"doc://com.proglove.Mark2SDK/documentation/ConnectSDK/PGImageManager":{"identifier":"doc:\/\/com.proglove.Mark2SDK\/documentation\/ConnectSDK\/PGImageManager","kind":"symbol","abstract":[{"text":"PGImageManager protocol containg the methods and properties for retrieving an image using photo feature","type":"text"}],"role":"symbol","url":"\/documentation\/connectsdk\/pgimagemanager","fragments":[{"text":"protocol","kind":"keyword"},{"kind":"text","text":" "},{"text":"PGImageManager","kind":"identifier"}],"navigatorTitle":[{"kind":"identifier","text":"PGImageManager"}],"title":"PGImageManager","type":"topic"},"doc://com.proglove.Mark2SDK/documentation/ConnectSDK/ConnectSDKVersionStringPtr":{"type":"topic","identifier":"doc:\/\/com.proglove.Mark2SDK\/documentation\/ConnectSDK\/ConnectSDKVersionStringPtr","kind":"symbol","fragments":[{"kind":"identifier","text":"ConnectSDKVersionStringPtr"}],"url":"\/documentation\/connectsdk\/connectsdkversionstringptr","title":"ConnectSDKVersionStringPtr","abstract":[{"text":"Project version string for ConnectSDK.","type":"text"}],"role":"symbol"},"doc://com.proglove.Mark2SDK/documentation/ConnectSDK/PGDeviceLockErrorDomain":{"kind":"symbol","type":"topic","identifier":"doc:\/\/com.proglove.Mark2SDK\/documentation\/ConnectSDK\/PGDeviceLockErrorDomain","fragments":[{"kind":"keyword","text":"let"},{"kind":"text","text":" "},{"text":"PGDeviceLockErrorDomain","kind":"identifier"},{"text":": ","kind":"text"},{"text":"String","preciseIdentifier":"s:SS","kind":"typeIdentifier"}],"navigatorTitle":[{"kind":"identifier","text":"PGDeviceLockErrorDomain"}],"url":"\/documentation\/connectsdk\/pgdevicelockerrordomain","title":"PGDeviceLockErrorDomain","abstract":[{"text":"Device Lock Error Domain","type":"text"}],"role":"symbol"},"doc://com.proglove.Mark2SDK/documentation/ConnectSDK/ConnectSDKVersionStringObject":{"kind":"symbol","type":"topic","identifier":"doc:\/\/com.proglove.Mark2SDK\/documentation\/ConnectSDK\/ConnectSDKVersionStringObject","fragments":[{"kind":"identifier","text":"ConnectSDKVersionStringObject"}],"url":"\/documentation\/connectsdk\/connectsdkversionstringobject","title":"ConnectSDKVersionStringObject","abstract":[{"text":"Project version string for ConnectSDK.","type":"text"}],"role":"symbol"},"doc://com.proglove.Mark2SDK/documentation/ConnectSDK/PGDisplayManager":{"type":"topic","identifier":"doc:\/\/com.proglove.Mark2SDK\/documentation\/ConnectSDK\/PGDisplayManager","kind":"symbol","fragments":[{"text":"protocol","kind":"keyword"},{"kind":"text","text":" "},{"text":"PGDisplayManager","kind":"identifier"}],"navigatorTitle":[{"text":"PGDisplayManager","kind":"identifier"}],"url":"\/documentation\/connectsdk\/pgdisplaymanager","title":"PGDisplayManager","abstract":[{"text":"Protocol contains all the display configuration related methods.","type":"text"}],"role":"symbol"},"doc://com.proglove.Mark2SDK/documentation/ConnectSDK/PGRefreshType":{"kind":"symbol","type":"topic","identifier":"doc:\/\/com.proglove.Mark2SDK\/documentation\/ConnectSDK\/PGRefreshType","fragments":[{"kind":"keyword","text":"enum"},{"kind":"text","text":" "},{"text":"PGRefreshType","kind":"identifier"}],"navigatorTitle":[{"text":"PGRefreshType","kind":"identifier"}],"url":"\/documentation\/connectsdk\/pgrefreshtype","title":"PGRefreshType","abstract":[{"type":"text","text":"The refresh type, the display should be using when setting a screen."}],"role":"symbol"},"doc://com.proglove.Mark2SDK/documentation/ConnectSDK/initate-connection":{"type":"topic","identifier":"doc:\/\/com.proglove.Mark2SDK\/documentation\/ConnectSDK\/initate-connection","kind":"article","url":"\/documentation\/connectsdk\/initate-connection","title":"Initiate Connection","abstract":[],"role":"article"},"doc://com.proglove.Mark2SDK/documentation/ConnectSDK/PGImageResolution":{"title":"PGImageResolution","kind":"symbol","fragments":[{"kind":"keyword","text":"enum"},{"text":" ","kind":"text"},{"kind":"identifier","text":"PGImageResolution"}],"navigatorTitle":[{"kind":"identifier","text":"PGImageResolution"}],"role":"symbol","identifier":"doc:\/\/com.proglove.Mark2SDK\/documentation\/ConnectSDK\/PGImageResolution","abstract":[],"url":"\/documentation\/connectsdk\/pgimageresolution","type":"topic"},"doc://com.proglove.Mark2SDK/documentation/ConnectSDK/PGLogFlag":{"type":"topic","identifier":"doc:\/\/com.proglove.Mark2SDK\/documentation\/ConnectSDK\/PGLogFlag","kind":"symbol","fragments":[{"kind":"keyword","text":"enum"},{"text":" ","kind":"text"},{"kind":"identifier","text":"PGLogFlag"}],"navigatorTitle":[{"kind":"identifier","text":"PGLogFlag"}],"url":"\/documentation\/connectsdk\/pglogflag","title":"PGLogFlag","abstract":[{"type":"text","text":"Log flags, used to determine the severity of a log message"}],"role":"symbol"},"doc://com.proglove.Mark2SDK/documentation/ConnectSDK/PGPeripheralLockState":{"type":"topic","abstract":[{"text":"The lock status of the scanner","type":"text"}],"identifier":"doc:\/\/com.proglove.Mark2SDK\/documentation\/ConnectSDK\/PGPeripheralLockState","role":"symbol","kind":"symbol","url":"\/documentation\/connectsdk\/pgperipherallockstate","fragments":[{"kind":"keyword","text":"enum"},{"kind":"text","text":" "},{"text":"PGPeripheralLockState","kind":"identifier"}],"title":"PGPeripheralLockState","navigatorTitle":[{"text":"PGPeripheralLockState","kind":"identifier"}]},"doc://com.proglove.Mark2SDK/documentation/ConnectSDK/PGLogging":{"kind":"symbol","type":"topic","identifier":"doc:\/\/com.proglove.Mark2SDK\/documentation\/ConnectSDK\/PGLogging","fragments":[{"kind":"keyword","text":"class"},{"kind":"text","text":" "},{"text":"PGLogging","kind":"identifier"}],"navigatorTitle":[{"kind":"identifier","text":"PGLogging"}],"url":"\/documentation\/connectsdk\/pglogging","title":"PGLogging","abstract":[{"text":"The logging class for the library","type":"text"}],"role":"symbol"},"doc://com.proglove.Mark2SDK/documentation/ConnectSDK/PGPeripheralState":{"role":"symbol","navigatorTitle":[{"kind":"identifier","text":"PGPeripheralState"}],"identifier":"doc:\/\/com.proglove.Mark2SDK\/documentation\/ConnectSDK\/PGPeripheralState","type":"topic","title":"PGPeripheralState","abstract":[{"text":"Values representing the current connection state of the peripheral","type":"text"}],"url":"\/documentation\/connectsdk\/pgperipheralstate","fragments":[{"kind":"keyword","text":"enum"},{"text":" ","kind":"text"},{"kind":"identifier","text":"PGPeripheralState"}],"kind":"symbol"},"doc://com.proglove.Mark2SDK/documentation/ConnectSDK/PGConfigurationProfile":{"url":"\/documentation\/connectsdk\/pgconfigurationprofile","fragments":[{"text":"class","kind":"keyword"},{"text":" ","kind":"text"},{"text":"PGConfigurationProfile","kind":"identifier"}],"identifier":"doc:\/\/com.proglove.Mark2SDK\/documentation\/ConnectSDK\/PGConfigurationProfile","type":"topic","role":"symbol","kind":"symbol","title":"PGConfigurationProfile","navigatorTitle":[{"text":"PGConfigurationProfile","kind":"identifier"}],"abstract":[{"text":"Configuration profile model class.","type":"text"}]},"doc://com.proglove.Mark2SDK/documentation/ConnectSDK":{"type":"topic","identifier":"doc:\/\/com.proglove.Mark2SDK\/documentation\/ConnectSDK","kind":"symbol","role":"collection","url":"\/documentation\/connectsdk","title":"ConnectSDK","abstract":[{"type":"text","text":"The "},{"inlineContent":[{"type":"text","text":"ProGlove ConnectSDK"}],"type":"strong"},{"text":" is a software development kit that enables integration between your iOS apps and the ProGlove system.","type":"text"}]},"doc://com.proglove.Mark2SDK/documentation/ConnectSDK/PGTemplateField":{"type":"topic","identifier":"doc:\/\/com.proglove.Mark2SDK\/documentation\/ConnectSDK\/PGTemplateField","kind":"symbol","fragments":[{"kind":"keyword","text":"class"},{"text":" ","kind":"text"},{"kind":"identifier","text":"PGTemplateField"}],"navigatorTitle":[{"text":"PGTemplateField","kind":"identifier"}],"url":"\/documentation\/connectsdk\/pgtemplatefield","title":"PGTemplateField","abstract":[{"type":"text","text":"This class represents the data, that should be displayed in a template field."}],"role":"symbol"},"doc://com.proglove.Mark2SDK/documentation/ConnectSDK/PGFeedbackApiError":{"kind":"symbol","identifier":"doc:\/\/com.proglove.Mark2SDK\/documentation\/ConnectSDK\/PGFeedbackApiError","type":"topic","fragments":[{"kind":"keyword","text":"enum"},{"kind":"text","text":" "},{"text":"PGFeedbackApiError","kind":"identifier"}],"navigatorTitle":[{"kind":"identifier","text":"PGFeedbackApiError"}],"url":"\/documentation\/connectsdk\/pgfeedbackapierror","title":"PGFeedbackApiError","abstract":[],"role":"symbol"},"doc://com.proglove.Mark2SDK/documentation/ConnectSDK/PGWearableApiErrorDomain":{"type":"topic","identifier":"doc:\/\/com.proglove.Mark2SDK\/documentation\/ConnectSDK\/PGWearableApiErrorDomain","kind":"symbol","fragments":[{"kind":"keyword","text":"let"},{"text":" ","kind":"text"},{"text":"PGWearableApiErrorDomain","kind":"identifier"},{"text":": ","kind":"text"},{"preciseIdentifier":"s:SS","text":"String","kind":"typeIdentifier"}],"navigatorTitle":[{"text":"PGWearableApiErrorDomain","kind":"identifier"}],"url":"\/documentation\/connectsdk\/pgwearableapierrordomain","title":"PGWearableApiErrorDomain","abstract":[{"type":"text","text":"The WearableApi error domain"}],"role":"symbol"},"doc://com.proglove.Mark2SDK/documentation/ConnectSDK/PGManager":{"kind":"symbol","identifier":"doc:\/\/com.proglove.Mark2SDK\/documentation\/ConnectSDK\/PGManager","type":"topic","fragments":[{"kind":"keyword","text":"class"},{"text":" ","kind":"text"},{"kind":"identifier","text":"PGManager"}],"navigatorTitle":[{"kind":"identifier","text":"PGManager"}],"url":"\/documentation\/connectsdk\/pgmanager","title":"PGManager","abstract":[{"text":"PGManager","type":"text"}],"role":"symbol"},"doc://com.proglove.Mark2SDK/documentation/ConnectSDK/PGConfigurationErrorDomain":{"type":"topic","identifier":"doc:\/\/com.proglove.Mark2SDK\/documentation\/ConnectSDK\/PGConfigurationErrorDomain","kind":"symbol","fragments":[{"kind":"keyword","text":"let"},{"text":" ","kind":"text"},{"text":"PGConfigurationErrorDomain","kind":"identifier"},{"text":": ","kind":"text"},{"preciseIdentifier":"s:SS","kind":"typeIdentifier","text":"String"}],"navigatorTitle":[{"text":"PGConfigurationErrorDomain","kind":"identifier"}],"url":"\/documentation\/connectsdk\/pgconfigurationerrordomain","title":"PGConfigurationErrorDomain","abstract":[{"text":"The ConfigurationApi error domain","type":"text"}],"role":"symbol"},"doc://com.proglove.Mark2SDK/documentation/ConnectSDK/PGDeviceInformationRequest":{"type":"topic","kind":"symbol","identifier":"doc:\/\/com.proglove.Mark2SDK\/documentation\/ConnectSDK\/PGDeviceInformationRequest","fragments":[{"text":"class","kind":"keyword"},{"text":" ","kind":"text"},{"text":"PGDeviceInformationRequest","kind":"identifier"}],"navigatorTitle":[{"text":"PGDeviceInformationRequest","kind":"identifier"}],"url":"\/documentation\/connectsdk\/pgdeviceinformationrequest","title":"PGDeviceInformationRequest","abstract":[{"text":"Request used for retreiving Device information","type":"text"}],"role":"symbol"},"doc://com.proglove.Mark2SDK/documentation/ConnectSDK/PGPeripheralDelegate":{"url":"\/documentation\/connectsdk\/pgperipheraldelegate","kind":"symbol","type":"topic","navigatorTitle":[{"kind":"identifier","text":"PGPeripheralDelegate"}],"fragments":[{"text":"protocol","kind":"keyword"},{"kind":"text","text":" "},{"text":"PGPeripheralDelegate","kind":"identifier"}],"role":"symbol","identifier":"doc:\/\/com.proglove.Mark2SDK\/documentation\/ConnectSDK\/PGPeripheralDelegate","title":"PGPeripheralDelegate","abstract":[{"type":"text","text":"The delegate protocol for the PG peripheral"}]},"doc://com.proglove.Mark2SDK/documentation/ConnectSDK/PGMockPeripheral":{"type":"topic","identifier":"doc:\/\/com.proglove.Mark2SDK\/documentation\/ConnectSDK\/PGMockPeripheral","kind":"symbol","role":"symbol","title":"PGMockPeripheral","abstract":[{"text":"A mock peripheral for use in testing","type":"text"}],"url":"\/documentation\/connectsdk\/pgmockperipheral","navigatorTitle":[{"text":"PGMockPeripheral","kind":"identifier"}],"fragments":[{"kind":"keyword","text":"class"},{"text":" ","kind":"text"},{"kind":"identifier","text":"PGMockPeripheral"}]},"doc://com.proglove.Mark2SDK/documentation/ConnectSDK/PGSetDisplayOrientationRequest":{"type":"topic","abstract":[{"text":"This object holds the data for updating a screen orientation on a ProGlove display device.","type":"text"}],"role":"symbol","navigatorTitle":[{"kind":"identifier","text":"PGSetDisplayOrientationRequest"}],"kind":"symbol","identifier":"doc:\/\/com.proglove.Mark2SDK\/documentation\/ConnectSDK\/PGSetDisplayOrientationRequest","fragments":[{"text":"class","kind":"keyword"},{"kind":"text","text":" "},{"kind":"identifier","text":"PGSetDisplayOrientationRequest"}],"url":"\/documentation\/connectsdk\/pgsetdisplayorientationrequest","title":"PGSetDisplayOrientationRequest"},"doc://com.proglove.Mark2SDK/documentation/ConnectSDK/ConnectSDKVersionString":{"type":"topic","identifier":"doc:\/\/com.proglove.Mark2SDK\/documentation\/ConnectSDK\/ConnectSDKVersionString","kind":"symbol","fragments":[{"kind":"identifier","text":"ConnectSDKVersionString"}],"url":"\/documentation\/connectsdk\/connectsdkversionstring","title":"ConnectSDKVersionString","abstract":[{"type":"text","text":"Project version string for ConnectSDK."}],"role":"symbol"},"doc://com.proglove.Mark2SDK/documentation/ConnectSDK/PGPeripheralErrorCentralHasRetriedConnectingKey":{"type":"topic","kind":"symbol","identifier":"doc:\/\/com.proglove.Mark2SDK\/documentation\/ConnectSDK\/PGPeripheralErrorCentralHasRetriedConnectingKey","fragments":[{"text":"let","kind":"keyword"},{"kind":"text","text":" "},{"text":"PGPeripheralErrorCentralHasRetriedConnectingKey","kind":"identifier"},{"text":": ","kind":"text"},{"text":"String","kind":"typeIdentifier","preciseIdentifier":"s:SS"}],"navigatorTitle":[{"kind":"identifier","text":"PGPeripheralErrorCentralHasRetriedConnectingKey"}],"url":"\/documentation\/connectsdk\/pgperipheralerrorcentralhasretriedconnectingkey","title":"PGPeripheralErrorCentralHasRetriedConnectingKey","abstract":[{"type":"text","text":"A NSNumber Boolean value indicating if the central has retried connection to this peripheral"}],"role":"symbol"},"doc://com.proglove.Mark2SDK/documentation/ConnectSDK/PGLogLevel":{"type":"topic","identifier":"doc:\/\/com.proglove.Mark2SDK\/documentation\/ConnectSDK\/PGLogLevel","kind":"symbol","fragments":[{"text":"enum","kind":"keyword"},{"text":" ","kind":"text"},{"kind":"identifier","text":"PGLogLevel"}],"navigatorTitle":[{"kind":"identifier","text":"PGLogLevel"}],"url":"\/documentation\/connectsdk\/pgloglevel","title":"PGLogLevel","abstract":[{"type":"text","text":"Log levels, used for filtering log messages"}],"role":"symbol"},"doc://com.proglove.Mark2SDK/documentation/ConnectSDK/PGCloudErrorDomain":{"kind":"symbol","type":"topic","identifier":"doc:\/\/com.proglove.Mark2SDK\/documentation\/ConnectSDK\/PGCloudErrorDomain","fragments":[{"kind":"keyword","text":"let"},{"text":" ","kind":"text"},{"text":"PGCloudErrorDomain","kind":"identifier"},{"text":": ","kind":"text"},{"kind":"typeIdentifier","preciseIdentifier":"s:SS","text":"String"}],"navigatorTitle":[{"kind":"identifier","text":"PGCloudErrorDomain"}],"url":"\/documentation\/connectsdk\/pgclouderrordomain","title":"PGCloudErrorDomain","abstract":[{"type":"text","text":"The Cloud Error Domain"}],"role":"symbol"},"doc://com.proglove.Mark2SDK/documentation/ConnectSDK/PGPeripheral":{"type":"topic","identifier":"doc:\/\/com.proglove.Mark2SDK\/documentation\/ConnectSDK\/PGPeripheral","kind":"symbol","role":"symbol","title":"PGPeripheral","abstract":[],"url":"\/documentation\/connectsdk\/pgperipheral","navigatorTitle":[{"text":"PGPeripheral","kind":"identifier"}],"fragments":[{"text":"class","kind":"keyword"},{"text":" ","kind":"text"},{"kind":"identifier","text":"PGPeripheral"}]},"doc://com.proglove.Mark2SDK/documentation/ConnectSDK/PGPeripheralErrorDomain":{"type":"topic","kind":"symbol","identifier":"doc:\/\/com.proglove.Mark2SDK\/documentation\/ConnectSDK\/PGPeripheralErrorDomain","fragments":[{"text":"let","kind":"keyword"},{"kind":"text","text":" "},{"text":"PGPeripheralErrorDomain","kind":"identifier"},{"kind":"text","text":": "},{"text":"String","kind":"typeIdentifier","preciseIdentifier":"s:SS"}],"navigatorTitle":[{"text":"PGPeripheralErrorDomain","kind":"identifier"}],"url":"\/documentation\/connectsdk\/pgperipheralerrordomain","title":"PGPeripheralErrorDomain","abstract":[{"type":"text","text":"The peripheral error domain"}],"role":"symbol"},"doc://com.proglove.Mark2SDK/documentation/ConnectSDK/PGPeripheralError":{"type":"topic","navigatorTitle":[{"kind":"identifier","text":"PGPeripheralError"}],"kind":"symbol","url":"\/documentation\/connectsdk\/pgperipheralerror","fragments":[{"kind":"keyword","text":"enum"},{"text":" ","kind":"text"},{"text":"PGPeripheralError","kind":"identifier"}],"identifier":"doc:\/\/com.proglove.Mark2SDK\/documentation\/ConnectSDK\/PGPeripheralError","role":"symbol","abstract":[{"text":"All PG peripheral error codes","type":"text"}],"title":"PGPeripheralError"},"doc://com.proglove.Mark2SDK/documentation/ConnectSDK/PGImage":{"kind":"symbol","identifier":"doc:\/\/com.proglove.Mark2SDK\/documentation\/ConnectSDK\/PGImage","type":"topic","fragments":[{"text":"class","kind":"keyword"},{"text":" ","kind":"text"},{"text":"PGImage","kind":"identifier"}],"navigatorTitle":[{"text":"PGImage","kind":"identifier"}],"url":"\/documentation\/connectsdk\/pgimage","title":"PGImage","abstract":[{"type":"text","text":"Object containing image data and image options"}],"role":"symbol"},"doc://com.proglove.Mark2SDK/documentation/ConnectSDK/PGCentralManagerDelegate":{"kind":"symbol","identifier":"doc:\/\/com.proglove.Mark2SDK\/documentation\/ConnectSDK\/PGCentralManagerDelegate","type":"topic","fragments":[{"kind":"keyword","text":"protocol"},{"text":" ","kind":"text"},{"text":"PGCentralManagerDelegate","kind":"identifier"}],"navigatorTitle":[{"kind":"identifier","text":"PGCentralManagerDelegate"}],"url":"\/documentation\/connectsdk\/pgcentralmanagerdelegate","title":"PGCentralManagerDelegate","abstract":[{"text":"PGCentralManagerDelegate","type":"text"}],"role":"symbol"},"doc://com.proglove.Mark2SDK/documentation/ConnectSDK/PGCommandParams":{"abstract":[{"text":"Holder for parameter that affect the execution of commands. For example the queueing behaviour.","type":"text"}],"url":"\/documentation\/connectsdk\/pgcommandparams","title":"PGCommandParams","role":"symbol","fragments":[{"text":"class","kind":"keyword"},{"text":" ","kind":"text"},{"text":"PGCommandParams","kind":"identifier"}],"identifier":"doc:\/\/com.proglove.Mark2SDK\/documentation\/ConnectSDK\/PGCommandParams","navigatorTitle":[{"kind":"identifier","text":"PGCommandParams"}],"kind":"symbol","type":"topic"},"introduction-graph.png":{"identifier":"introduction-graph.png","alt":"Introduction","type":"image","variants":[{"url":"\/images\/introduction-graph.png","traits":["1x","light"]}]},"doc://com.proglove.Mark2SDK/documentation/ConnectSDK/PGManagerState":{"kind":"symbol","identifier":"doc:\/\/com.proglove.Mark2SDK\/documentation\/ConnectSDK\/PGManagerState","type":"topic","fragments":[{"text":"enum","kind":"keyword"},{"text":" ","kind":"text"},{"text":"PGManagerState","kind":"identifier"}],"navigatorTitle":[{"text":"PGManagerState","kind":"identifier"}],"url":"\/documentation\/connectsdk\/pgmanagerstate","title":"PGManagerState","abstract":[{"text":"Represents the current state of a PGManager.","type":"text"}],"role":"symbol"},"doc://com.proglove.Mark2SDK/documentation/ConnectSDK/PGPairingQRGeneratorErrorCorrectionLevel":{"abstract":[{"text":"The PG Pairing QR error correction level","type":"text"}],"role":"symbol","identifier":"doc:\/\/com.proglove.Mark2SDK\/documentation\/ConnectSDK\/PGPairingQRGeneratorErrorCorrectionLevel","navigatorTitle":[{"text":"PGPairingQRGeneratorErrorCorrectionLevel","kind":"identifier"}],"title":"PGPairingQRGeneratorErrorCorrectionLevel","url":"\/documentation\/connectsdk\/pgpairingqrgeneratorerrorcorrectionlevel","fragments":[{"text":"enum","kind":"keyword"},{"text":" ","kind":"text"},{"kind":"identifier","text":"PGPairingQRGeneratorErrorCorrectionLevel"}],"type":"topic","kind":"symbol"},"doc://com.proglove.Mark2SDK/documentation/ConnectSDK/ConnectSDKVersionNumber":{"kind":"symbol","identifier":"doc:\/\/com.proglove.Mark2SDK\/documentation\/ConnectSDK\/ConnectSDKVersionNumber","type":"topic","fragments":[{"kind":"identifier","text":"ConnectSDKVersionNumber"}],"url":"\/documentation\/connectsdk\/connectsdkversionnumber","title":"ConnectSDKVersionNumber","abstract":[{"text":"Project version number for ConnectSDK.","type":"text"}],"role":"symbol"},"doc://com.proglove.Mark2SDK/documentation/ConnectSDK/PGDisplayApiErrorDomain":{"kind":"symbol","identifier":"doc:\/\/com.proglove.Mark2SDK\/documentation\/ConnectSDK\/PGDisplayApiErrorDomain","type":"topic","fragments":[{"text":"let","kind":"keyword"},{"text":" ","kind":"text"},{"kind":"identifier","text":"PGDisplayApiErrorDomain"},{"text":": ","kind":"text"},{"text":"String","preciseIdentifier":"s:SS","kind":"typeIdentifier"}],"navigatorTitle":[{"kind":"identifier","text":"PGDisplayApiErrorDomain"}],"url":"\/documentation\/connectsdk\/pgdisplayapierrordomain","title":"PGDisplayApiErrorDomain","abstract":[{"type":"text","text":"The scanner display api error domain."}],"role":"symbol"},"doc://com.proglove.Mark2SDK/documentation/ConnectSDK/PGConfigurationApiError":{"kind":"symbol","identifier":"doc:\/\/com.proglove.Mark2SDK\/documentation\/ConnectSDK\/PGConfigurationApiError","type":"topic","fragments":[{"text":"enum","kind":"keyword"},{"text":" ","kind":"text"},{"kind":"identifier","text":"PGConfigurationApiError"}],"navigatorTitle":[{"kind":"identifier","text":"PGConfigurationApiError"}],"url":"\/documentation\/connectsdk\/pgconfigurationapierror","title":"PGConfigurationApiError","abstract":[{"type":"text","text":"PG configuration api error codes"}],"role":"symbol"},"doc://com.proglove.Mark2SDK/documentation/ConnectSDK/PGScreenData":{"kind":"symbol","identifier":"doc:\/\/com.proglove.Mark2SDK\/documentation\/ConnectSDK\/PGScreenData","type":"topic","fragments":[{"text":"class","kind":"keyword"},{"text":" ","kind":"text"},{"text":"PGScreenData","kind":"identifier"}],"navigatorTitle":[{"text":"PGScreenData","kind":"identifier"}],"url":"\/documentation\/connectsdk\/pgscreendata","title":"PGScreenData","abstract":[{"type":"text","text":"This object holds the data for updating a screen on a ProGlove display device."}],"role":"symbol"},"doc://com.proglove.Mark2SDK/documentation/ConnectSDK/PGPairingQRGeneratorOptions":{"kind":"symbol","type":"topic","identifier":"doc:\/\/com.proglove.Mark2SDK\/documentation\/ConnectSDK\/PGPairingQRGeneratorOptions","fragments":[{"text":"class","kind":"keyword"},{"kind":"text","text":" "},{"kind":"identifier","text":"PGPairingQRGeneratorOptions"}],"navigatorTitle":[{"kind":"identifier","text":"PGPairingQRGeneratorOptions"}],"url":"\/documentation\/connectsdk\/pgpairingqrgeneratoroptions","title":"PGPairingQRGeneratorOptions","abstract":[{"type":"text","text":"Options for generating QR pairing image"}],"role":"symbol"},"doc://com.proglove.Mark2SDK/documentation/ConnectSDK/PGCloudConnectionDelegate":{"kind":"symbol","identifier":"doc:\/\/com.proglove.Mark2SDK\/documentation\/ConnectSDK\/PGCloudConnectionDelegate","type":"topic","fragments":[{"kind":"keyword","text":"protocol"},{"text":" ","kind":"text"},{"kind":"identifier","text":"PGCloudConnectionDelegate"}],"navigatorTitle":[{"kind":"identifier","text":"PGCloudConnectionDelegate"}],"url":"\/documentation\/connectsdk\/pgcloudconnectiondelegate","title":"PGCloudConnectionDelegate","abstract":[],"role":"symbol"},"doc://com.proglove.Mark2SDK/documentation/ConnectSDK/PGCaptureImageRequest":{"title":"PGCaptureImageRequest","url":"\/documentation\/connectsdk\/pgcaptureimagerequest","fragments":[{"kind":"keyword","text":"class"},{"kind":"text","text":" "},{"kind":"identifier","text":"PGCaptureImageRequest"}],"navigatorTitle":[{"text":"PGCaptureImageRequest","kind":"identifier"}],"role":"symbol","identifier":"doc:\/\/com.proglove.Mark2SDK\/documentation\/ConnectSDK\/PGCaptureImageRequest","abstract":[{"text":"PGCaptureImageRequest","type":"text"}],"kind":"symbol","type":"topic"},"doc://com.proglove.Mark2SDK/documentation/ConnectSDK/PGScannedBarcodeResult":{"kind":"symbol","type":"topic","identifier":"doc:\/\/com.proglove.Mark2SDK\/documentation\/ConnectSDK\/PGScannedBarcodeResult","fragments":[{"text":"class","kind":"keyword"},{"text":" ","kind":"text"},{"kind":"identifier","text":"PGScannedBarcodeResult"}],"navigatorTitle":[{"text":"PGScannedBarcodeResult","kind":"identifier"}],"url":"\/documentation\/connectsdk\/pgscannedbarcoderesult","title":"PGScannedBarcodeResult","abstract":[{"type":"text","text":"PGScannedBarcodeResult"}],"role":"symbol"}},"variantOverrides":[{"traits":[{"interfaceLanguage":"occ"}],"patch":[{"op":"replace","path":"\/identifier\/interfaceLanguage","value":"occ"},{"op":"replace","path":"\/topicSections","value":[{"title":"Essentials","identifiers":["doc:\/\/com.proglove.Mark2SDK\/documentation\/ConnectSDK\/initate-connection"]},{"identifiers":["doc:\/\/com.proglove.Mark2SDK\/documentation\/ConnectSDK\/PGDeviceInformation","doc:\/\/com.proglove.Mark2SDK\/documentation\/ConnectSDK\/PGScreenData"],"title":"Models"},{"title":"Classes","identifiers":["doc:\/\/com.proglove.Mark2SDK\/documentation\/ConnectSDK\/PGCaptureImageRequest","doc:\/\/com.proglove.Mark2SDK\/documentation\/ConnectSDK\/PGCentralManager","doc:\/\/com.proglove.Mark2SDK\/documentation\/ConnectSDK\/PGCommand","doc:\/\/com.proglove.Mark2SDK\/documentation\/ConnectSDK\/PGCommandParams","doc:\/\/com.proglove.Mark2SDK\/documentation\/ConnectSDK\/PGConfigurationProfile","doc:\/\/com.proglove.Mark2SDK\/documentation\/ConnectSDK\/PGDeviceInformationRequest","doc:\/\/com.proglove.Mark2SDK\/documentation\/ConnectSDK\/PGFeedbackRequest","doc:\/\/com.proglove.Mark2SDK\/documentation\/ConnectSDK\/PGImage","doc:\/\/com.proglove.Mark2SDK\/documentation\/ConnectSDK\/PGLogging","doc:\/\/com.proglove.Mark2SDK\/documentation\/ConnectSDK\/PGManager","doc:\/\/com.proglove.Mark2SDK\/documentation\/ConnectSDK\/PGMockPeripheral","doc:\/\/com.proglove.Mark2SDK\/documentation\/ConnectSDK\/PGPairingQR","doc:\/\/com.proglove.Mark2SDK\/documentation\/ConnectSDK\/PGPairingQRGeneratorOptions","doc:\/\/com.proglove.Mark2SDK\/documentation\/ConnectSDK\/PGPeripheral","doc:\/\/com.proglove.Mark2SDK\/documentation\/ConnectSDK\/PGScannedBarcodeResult","doc:\/\/com.proglove.Mark2SDK\/documentation\/ConnectSDK\/PGSetDisplayOrientationRequest","doc:\/\/com.proglove.Mark2SDK\/documentation\/ConnectSDK\/PGTemplateField"]},{"identifiers":["doc:\/\/com.proglove.Mark2SDK\/documentation\/ConnectSDK\/PGCentralManagerDelegate","doc:\/\/com.proglove.Mark2SDK\/documentation\/ConnectSDK\/PGCloudConnectionDelegate","doc:\/\/com.proglove.Mark2SDK\/documentation\/ConnectSDK\/PGConfigurationManager","doc:\/\/com.proglove.Mark2SDK\/documentation\/ConnectSDK\/PGConfigurationManagerDelegate","doc:\/\/com.proglove.Mark2SDK\/documentation\/ConnectSDK\/PGDisplayManager","doc:\/\/com.proglove.Mark2SDK\/documentation\/ConnectSDK\/PGFeedbackManager","doc:\/\/com.proglove.Mark2SDK\/documentation\/ConnectSDK\/PGFirmwareUpdateManager","doc:\/\/com.proglove.Mark2SDK\/documentation\/ConnectSDK\/PGFirmwareUpdateManagerDelegate","doc:\/\/com.proglove.Mark2SDK\/documentation\/ConnectSDK\/PGImageManager","doc:\/\/com.proglove.Mark2SDK\/documentation\/ConnectSDK\/PGLoggingDelegate","doc:\/\/com.proglove.Mark2SDK\/documentation\/ConnectSDK\/PGManagerDelegate","doc:\/\/com.proglove.Mark2SDK\/documentation\/ConnectSDK\/PGPeripheralDelegate"],"title":"Protocols"},{"title":"Variables","identifiers":["doc:\/\/com.proglove.Mark2SDK\/documentation\/ConnectSDK\/ConnectSDKVersionNumber","doc:\/\/com.proglove.Mark2SDK\/documentation\/ConnectSDK\/ConnectSDKVersionString","doc:\/\/com.proglove.Mark2SDK\/documentation\/ConnectSDK\/ConnectSDKVersionStringObject","doc:\/\/com.proglove.Mark2SDK\/documentation\/ConnectSDK\/ConnectSDKVersionStringPtr","doc:\/\/com.proglove.Mark2SDK\/documentation\/ConnectSDK\/PGCloudBulkErrorDomain","doc:\/\/com.proglove.Mark2SDK\/documentation\/ConnectSDK\/PGCloudErrorDomain","doc:\/\/com.proglove.Mark2SDK\/documentation\/ConnectSDK\/PGCloudFleetErrorDomain","doc:\/\/com.proglove.Mark2SDK\/documentation\/ConnectSDK\/PGConfigurationErrorDomain","doc:\/\/com.proglove.Mark2SDK\/documentation\/ConnectSDK\/PGDeviceLockErrorDomain","doc:\/\/com.proglove.Mark2SDK\/documentation\/ConnectSDK\/PGDisplayApiErrorDomain","doc:\/\/com.proglove.Mark2SDK\/documentation\/ConnectSDK\/PGFeedbackApiErrorDomain","doc:\/\/com.proglove.Mark2SDK\/documentation\/ConnectSDK\/PGFirmwareUpdateErrorDomain","doc:\/\/com.proglove.Mark2SDK\/documentation\/ConnectSDK\/PGPairingQRGeneratorErrorDomain","doc:\/\/com.proglove.Mark2SDK\/documentation\/ConnectSDK\/PGPeripheralErrorCentralHasRetriedConnectingKey","doc:\/\/com.proglove.Mark2SDK\/documentation\/ConnectSDK\/PGPeripheralErrorDomain","doc:\/\/com.proglove.Mark2SDK\/documentation\/ConnectSDK\/PGPeripheralErrorIncompatibleModelNumberKey","doc:\/\/com.proglove.Mark2SDK\/documentation\/ConnectSDK\/PGPeripheralErrorServiceKey","doc:\/\/com.proglove.Mark2SDK\/documentation\/ConnectSDK\/PGURLErrorDomain","doc:\/\/com.proglove.Mark2SDK\/documentation\/ConnectSDK\/PGWearableApiErrorDomain"]},{"identifiers":["doc:\/\/com.proglove.Mark2SDK\/documentation\/ConnectSDK\/PGButtonTriggerEventType","doc:\/\/com.proglove.Mark2SDK\/documentation\/ConnectSDK\/PGCloudConnectionStatus","doc:\/\/com.proglove.Mark2SDK\/documentation\/ConnectSDK\/PGConfigurationApiError","doc:\/\/com.proglove.Mark2SDK\/documentation\/ConnectSDK\/PGDeviceLockError","doc:\/\/com.proglove.Mark2SDK\/documentation\/ConnectSDK\/PGDisplayApiError","doc:\/\/com.proglove.Mark2SDK\/documentation\/ConnectSDK\/PGFeedbackApiError","doc:\/\/com.proglove.Mark2SDK\/documentation\/ConnectSDK\/PGImageResolution","doc:\/\/com.proglove.Mark2SDK\/documentation\/ConnectSDK\/PGLogFlag","doc:\/\/com.proglove.Mark2SDK\/documentation\/ConnectSDK\/PGLogLevel","doc:\/\/com.proglove.Mark2SDK\/documentation\/ConnectSDK\/PGManagerState","doc:\/\/com.proglove.Mark2SDK\/documentation\/ConnectSDK\/PGOrientation","doc:\/\/com.proglove.Mark2SDK\/documentation\/ConnectSDK\/PGPairingQRGeneratorApiError","doc:\/\/com.proglove.Mark2SDK\/documentation\/ConnectSDK\/PGPairingQRGeneratorErrorCorrectionLevel","doc:\/\/com.proglove.Mark2SDK\/documentation\/ConnectSDK\/PGPeripheralError","doc:\/\/com.proglove.Mark2SDK\/documentation\/ConnectSDK\/PGPeripheralLockState","doc:\/\/com.proglove.Mark2SDK\/documentation\/ConnectSDK\/PGPeripheralState","doc:\/\/com.proglove.Mark2SDK\/documentation\/ConnectSDK\/PGPredefinedFeedback","doc:\/\/com.proglove.Mark2SDK\/documentation\/ConnectSDK\/PGRefreshType","doc:\/\/com.proglove.Mark2SDK\/documentation\/ConnectSDK\/PGWearableApiError"],"title":"Enumerations"}]},{"value":null,"op":"add","path":"\/relationshipsSections"},{"path":"\/seeAlsoSections","value":null,"op":"add"},{"value":"PGFeedbackManager","path":"\/references\/doc:~1~1com.proglove.Mark2SDK~1documentation~1ConnectSDK~1PGFeedbackManager\/title","op":"replace"},{"op":"replace","path":"\/references\/doc:~1~1com.proglove.Mark2SDK~1documentation~1ConnectSDK~1PGFeedbackManager\/fragments","value":[{"kind":"identifier","text":"PGFeedbackManager"}]},{"value":"PGCloudBulkErrorDomain","path":"\/references\/doc:~1~1com.proglove.Mark2SDK~1documentation~1ConnectSDK~1PGCloudBulkErrorDomain\/title","op":"replace"},{"op":"replace","path":"\/references\/doc:~1~1com.proglove.Mark2SDK~1documentation~1ConnectSDK~1PGCloudBulkErrorDomain\/fragments","value":[{"text":"PGCloudBulkErrorDomain","kind":"identifier"}]},{"value":"PGFeedbackApiErrorDomain","op":"replace","path":"\/references\/doc:~1~1com.proglove.Mark2SDK~1documentation~1ConnectSDK~1PGFeedbackApiErrorDomain\/title"},{"value":[{"kind":"identifier","text":"PGFeedbackApiErrorDomain"}],"op":"replace","path":"\/references\/doc:~1~1com.proglove.Mark2SDK~1documentation~1ConnectSDK~1PGFeedbackApiErrorDomain\/fragments"},{"op":"replace","path":"\/references\/doc:~1~1com.proglove.Mark2SDK~1documentation~1ConnectSDK~1PGPeripheralErrorIncompatibleModelNumberKey\/title","value":"PGPeripheralErrorIncompatibleModelNumberKey"},{"path":"\/references\/doc:~1~1com.proglove.Mark2SDK~1documentation~1ConnectSDK~1PGPeripheralErrorIncompatibleModelNumberKey\/fragments","value":[{"kind":"identifier","text":"PGPeripheralErrorIncompatibleModelNumberKey"}],"op":"replace"},{"path":"\/references\/doc:~1~1com.proglove.Mark2SDK~1documentation~1ConnectSDK~1PGDisplayApiError\/title","value":"PGDisplayApiError","op":"replace"},{"op":"replace","path":"\/references\/doc:~1~1com.proglove.Mark2SDK~1documentation~1ConnectSDK~1PGDisplayApiError\/fragments","value":[{"kind":"identifier","text":"PGDisplayApiError"}]},{"path":"\/references\/doc:~1~1com.proglove.Mark2SDK~1documentation~1ConnectSDK~1PGURLErrorDomain\/title","value":"PGURLErrorDomain","op":"replace"},{"path":"\/references\/doc:~1~1com.proglove.Mark2SDK~1documentation~1ConnectSDK~1PGURLErrorDomain\/fragments","op":"replace","value":[{"text":"PGURLErrorDomain","kind":"identifier"}]},{"value":"PGConfigurationManagerDelegate","op":"replace","path":"\/references\/doc:~1~1com.proglove.Mark2SDK~1documentation~1ConnectSDK~1PGConfigurationManagerDelegate\/title"},{"value":[{"kind":"identifier","text":"PGConfigurationManagerDelegate"}],"op":"replace","path":"\/references\/doc:~1~1com.proglove.Mark2SDK~1documentation~1ConnectSDK~1PGConfigurationManagerDelegate\/fragments"},{"path":"\/references\/doc:~1~1com.proglove.Mark2SDK~1documentation~1ConnectSDK~1PGPairingQRGeneratorApiError\/title","value":"PGPairingQRGeneratorApiError","op":"replace"},{"op":"replace","path":"\/references\/doc:~1~1com.proglove.Mark2SDK~1documentation~1ConnectSDK~1PGPairingQRGeneratorApiError\/fragments","value":[{"kind":"identifier","text":"PGPairingQRGeneratorApiError"}]},{"value":"PGButtonTriggerEventType","op":"replace","path":"\/references\/doc:~1~1com.proglove.Mark2SDK~1documentation~1ConnectSDK~1PGButtonTriggerEventType\/title"},{"op":"replace","value":[{"text":"PGButtonTriggerEventType","kind":"identifier"}],"path":"\/references\/doc:~1~1com.proglove.Mark2SDK~1documentation~1ConnectSDK~1PGButtonTriggerEventType\/fragments"},{"value":"PGFirmwareUpdateManager","op":"replace","path":"\/references\/doc:~1~1com.proglove.Mark2SDK~1documentation~1ConnectSDK~1PGFirmwareUpdateManager\/title"},{"path":"\/references\/doc:~1~1com.proglove.Mark2SDK~1documentation~1ConnectSDK~1PGFirmwareUpdateManager\/fragments","op":"replace","value":[{"kind":"identifier","text":"PGFirmwareUpdateManager"}]},{"value":"PGPeripheralErrorServiceKey","path":"\/references\/doc:~1~1com.proglove.Mark2SDK~1documentation~1ConnectSDK~1PGPeripheralErrorServiceKey\/title","op":"replace"},{"op":"replace","path":"\/references\/doc:~1~1com.proglove.Mark2SDK~1documentation~1ConnectSDK~1PGPeripheralErrorServiceKey\/fragments","value":[{"text":"PGPeripheralErrorServiceKey","kind":"identifier"}]},{"op":"replace","value":"PGCloudConnectionStatus","path":"\/references\/doc:~1~1com.proglove.Mark2SDK~1documentation~1ConnectSDK~1PGCloudConnectionStatus\/title"},{"path":"\/references\/doc:~1~1com.proglove.Mark2SDK~1documentation~1ConnectSDK~1PGCloudConnectionStatus\/fragments","value":[{"text":"PGCloudConnectionStatus","kind":"identifier"}],"op":"replace"},{"op":"replace","value":"PGManagerDelegate","path":"\/references\/doc:~1~1com.proglove.Mark2SDK~1documentation~1ConnectSDK~1PGManagerDelegate\/title"},{"op":"replace","value":[{"kind":"identifier","text":"PGManagerDelegate"}],"path":"\/references\/doc:~1~1com.proglove.Mark2SDK~1documentation~1ConnectSDK~1PGManagerDelegate\/fragments"},{"value":"PGWearableApiError","path":"\/references\/doc:~1~1com.proglove.Mark2SDK~1documentation~1ConnectSDK~1PGWearableApiError\/title","op":"replace"},{"value":[{"kind":"identifier","text":"PGWearableApiError"}],"path":"\/references\/doc:~1~1com.proglove.Mark2SDK~1documentation~1ConnectSDK~1PGWearableApiError\/fragments","op":"replace"},{"op":"replace","value":"PGCentralManager","path":"\/references\/doc:~1~1com.proglove.Mark2SDK~1documentation~1ConnectSDK~1PGCentralManager\/title"},{"op":"replace","path":"\/references\/doc:~1~1com.proglove.Mark2SDK~1documentation~1ConnectSDK~1PGCentralManager\/fragments","value":[{"text":"PGCentralManager","kind":"identifier"}]},{"path":"\/references\/doc:~1~1com.proglove.Mark2SDK~1documentation~1ConnectSDK~1PGFirmwareUpdateErrorDomain\/title","value":"PGFirmwareUpdateErrorDomain","op":"replace"},{"value":[{"kind":"identifier","text":"PGFirmwareUpdateErrorDomain"}],"path":"\/references\/doc:~1~1com.proglove.Mark2SDK~1documentation~1ConnectSDK~1PGFirmwareUpdateErrorDomain\/fragments","op":"replace"},{"value":"PGConfigurationManager","path":"\/references\/doc:~1~1com.proglove.Mark2SDK~1documentation~1ConnectSDK~1PGConfigurationManager\/title","op":"replace"},{"value":[{"kind":"identifier","text":"PGConfigurationManager"}],"op":"replace","path":"\/references\/doc:~1~1com.proglove.Mark2SDK~1documentation~1ConnectSDK~1PGConfigurationManager\/fragments"},{"path":"\/references\/doc:~1~1com.proglove.Mark2SDK~1documentation~1ConnectSDK~1PGPairingQRGeneratorErrorDomain\/title","op":"replace","value":"PGPairingQRGeneratorErrorDomain"},{"value":[{"kind":"identifier","text":"PGPairingQRGeneratorErrorDomain"}],"path":"\/references\/doc:~1~1com.proglove.Mark2SDK~1documentation~1ConnectSDK~1PGPairingQRGeneratorErrorDomain\/fragments","op":"replace"},{"value":"PGOrientation","path":"\/references\/doc:~1~1com.proglove.Mark2SDK~1documentation~1ConnectSDK~1PGOrientation\/title","op":"replace"},{"value":[{"kind":"identifier","text":"PGOrientation"}],"op":"replace","path":"\/references\/doc:~1~1com.proglove.Mark2SDK~1documentation~1ConnectSDK~1PGOrientation\/fragments"},{"path":"\/references\/doc:~1~1com.proglove.Mark2SDK~1documentation~1ConnectSDK~1PGDeviceInformation\/title","value":"PGDeviceInformation","op":"replace"},{"op":"replace","path":"\/references\/doc:~1~1com.proglove.Mark2SDK~1documentation~1ConnectSDK~1PGDeviceInformation\/fragments","value":[{"text":"PGDeviceInformation","kind":"identifier"}]},{"value":"PGPredefinedFeedback","path":"\/references\/doc:~1~1com.proglove.Mark2SDK~1documentation~1ConnectSDK~1PGPredefinedFeedback\/title","op":"replace"},{"op":"replace","path":"\/references\/doc:~1~1com.proglove.Mark2SDK~1documentation~1ConnectSDK~1PGPredefinedFeedback\/fragments","value":[{"text":"PGPredefinedFeedback","kind":"identifier"}]},{"value":"PGCloudFleetErrorDomain","path":"\/references\/doc:~1~1com.proglove.Mark2SDK~1documentation~1ConnectSDK~1PGCloudFleetErrorDomain\/title","op":"replace"},{"path":"\/references\/doc:~1~1com.proglove.Mark2SDK~1documentation~1ConnectSDK~1PGCloudFleetErrorDomain\/fragments","op":"replace","value":[{"text":"PGCloudFleetErrorDomain","kind":"identifier"}]},{"op":"replace","path":"\/references\/doc:~1~1com.proglove.Mark2SDK~1documentation~1ConnectSDK~1PGFeedbackRequest\/title","value":"PGFeedbackRequest"},{"value":[{"text":"PGFeedbackRequest","kind":"identifier"}],"path":"\/references\/doc:~1~1com.proglove.Mark2SDK~1documentation~1ConnectSDK~1PGFeedbackRequest\/fragments","op":"replace"},{"path":"\/references\/doc:~1~1com.proglove.Mark2SDK~1documentation~1ConnectSDK~1PGDeviceLockError\/title","op":"replace","value":"PGDeviceLockError"},{"value":[{"text":"PGDeviceLockError","kind":"identifier"}],"path":"\/references\/doc:~1~1com.proglove.Mark2SDK~1documentation~1ConnectSDK~1PGDeviceLockError\/fragments","op":"replace"},{"op":"replace","value":"PGPairingQR","path":"\/references\/doc:~1~1com.proglove.Mark2SDK~1documentation~1ConnectSDK~1PGPairingQR\/title"},{"value":[{"kind":"identifier","text":"PGPairingQR"}],"path":"\/references\/doc:~1~1com.proglove.Mark2SDK~1documentation~1ConnectSDK~1PGPairingQR\/fragments","op":"replace"},{"value":"PGLoggingDelegate","op":"replace","path":"\/references\/doc:~1~1com.proglove.Mark2SDK~1documentation~1ConnectSDK~1PGLoggingDelegate\/title"},{"op":"replace","path":"\/references\/doc:~1~1com.proglove.Mark2SDK~1documentation~1ConnectSDK~1PGLoggingDelegate\/fragments","value":[{"text":"PGLoggingDelegate","kind":"identifier"}]},{"path":"\/references\/doc:~1~1com.proglove.Mark2SDK~1documentation~1ConnectSDK~1PGFirmwareUpdateManagerDelegate\/title","op":"replace","value":"PGFirmwareUpdateManagerDelegate"},{"value":[{"text":"PGFirmwareUpdateManagerDelegate","kind":"identifier"}],"op":"replace","path":"\/references\/doc:~1~1com.proglove.Mark2SDK~1documentation~1ConnectSDK~1PGFirmwareUpdateManagerDelegate\/fragments"},{"value":"PGCommand","path":"\/references\/doc:~1~1com.proglove.Mark2SDK~1documentation~1ConnectSDK~1PGCommand\/title","op":"replace"},{"op":"replace","value":[{"text":"PGCommand","kind":"identifier"}],"path":"\/references\/doc:~1~1com.proglove.Mark2SDK~1documentation~1ConnectSDK~1PGCommand\/fragments"},{"value":"PGImageManager","op":"replace","path":"\/references\/doc:~1~1com.proglove.Mark2SDK~1documentation~1ConnectSDK~1PGImageManager\/title"},{"value":[{"kind":"identifier","text":"PGImageManager"}],"op":"replace","path":"\/references\/doc:~1~1com.proglove.Mark2SDK~1documentation~1ConnectSDK~1PGImageManager\/fragments"},{"op":"replace","value":"PGDeviceLockErrorDomain","path":"\/references\/doc:~1~1com.proglove.Mark2SDK~1documentation~1ConnectSDK~1PGDeviceLockErrorDomain\/title"},{"path":"\/references\/doc:~1~1com.proglove.Mark2SDK~1documentation~1ConnectSDK~1PGDeviceLockErrorDomain\/fragments","op":"replace","value":[{"text":"PGDeviceLockErrorDomain","kind":"identifier"}]},{"value":"PGDisplayManager","op":"replace","path":"\/references\/doc:~1~1com.proglove.Mark2SDK~1documentation~1ConnectSDK~1PGDisplayManager\/title"},{"value":[{"kind":"identifier","text":"PGDisplayManager"}],"op":"replace","path":"\/references\/doc:~1~1com.proglove.Mark2SDK~1documentation~1ConnectSDK~1PGDisplayManager\/fragments"},{"op":"replace","path":"\/references\/doc:~1~1com.proglove.Mark2SDK~1documentation~1ConnectSDK~1PGRefreshType\/title","value":"PGRefreshType"},{"value":[{"text":"PGRefreshType","kind":"identifier"}],"path":"\/references\/doc:~1~1com.proglove.Mark2SDK~1documentation~1ConnectSDK~1PGRefreshType\/fragments","op":"replace"},{"op":"replace","path":"\/references\/doc:~1~1com.proglove.Mark2SDK~1documentation~1ConnectSDK~1PGImageResolution\/title","value":"PGImageResolution"},{"op":"replace","path":"\/references\/doc:~1~1com.proglove.Mark2SDK~1documentation~1ConnectSDK~1PGImageResolution\/fragments","value":[{"kind":"identifier","text":"PGImageResolution"}]},{"value":"PGLogFlag","op":"replace","path":"\/references\/doc:~1~1com.proglove.Mark2SDK~1documentation~1ConnectSDK~1PGLogFlag\/title"},{"op":"replace","path":"\/references\/doc:~1~1com.proglove.Mark2SDK~1documentation~1ConnectSDK~1PGLogFlag\/fragments","value":[{"text":"PGLogFlag","kind":"identifier"}]},{"value":"PGPeripheralLockState","op":"replace","path":"\/references\/doc:~1~1com.proglove.Mark2SDK~1documentation~1ConnectSDK~1PGPeripheralLockState\/title"},{"op":"replace","path":"\/references\/doc:~1~1com.proglove.Mark2SDK~1documentation~1ConnectSDK~1PGPeripheralLockState\/fragments","value":[{"kind":"identifier","text":"PGPeripheralLockState"}]},{"path":"\/references\/doc:~1~1com.proglove.Mark2SDK~1documentation~1ConnectSDK~1PGLogging\/title","value":"PGLogging","op":"replace"},{"op":"replace","value":[{"text":"PGLogging","kind":"identifier"}],"path":"\/references\/doc:~1~1com.proglove.Mark2SDK~1documentation~1ConnectSDK~1PGLogging\/fragments"},{"value":"PGPeripheralState","op":"replace","path":"\/references\/doc:~1~1com.proglove.Mark2SDK~1documentation~1ConnectSDK~1PGPeripheralState\/title"},{"path":"\/references\/doc:~1~1com.proglove.Mark2SDK~1documentation~1ConnectSDK~1PGPeripheralState\/fragments","value":[{"text":"PGPeripheralState","kind":"identifier"}],"op":"replace"},{"value":"PGConfigurationProfile","op":"replace","path":"\/references\/doc:~1~1com.proglove.Mark2SDK~1documentation~1ConnectSDK~1PGConfigurationProfile\/title"},{"value":[{"text":"PGConfigurationProfile","kind":"identifier"}],"op":"replace","path":"\/references\/doc:~1~1com.proglove.Mark2SDK~1documentation~1ConnectSDK~1PGConfigurationProfile\/fragments"},{"op":"replace","value":"PGTemplateField","path":"\/references\/doc:~1~1com.proglove.Mark2SDK~1documentation~1ConnectSDK~1PGTemplateField\/title"},{"path":"\/references\/doc:~1~1com.proglove.Mark2SDK~1documentation~1ConnectSDK~1PGTemplateField\/fragments","op":"replace","value":[{"kind":"identifier","text":"PGTemplateField"}]},{"op":"replace","value":"PGFeedbackApiError","path":"\/references\/doc:~1~1com.proglove.Mark2SDK~1documentation~1ConnectSDK~1PGFeedbackApiError\/title"},{"value":[{"kind":"identifier","text":"PGFeedbackApiError"}],"path":"\/references\/doc:~1~1com.proglove.Mark2SDK~1documentation~1ConnectSDK~1PGFeedbackApiError\/fragments","op":"replace"},{"op":"replace","value":"PGWearableApiErrorDomain","path":"\/references\/doc:~1~1com.proglove.Mark2SDK~1documentation~1ConnectSDK~1PGWearableApiErrorDomain\/title"},{"path":"\/references\/doc:~1~1com.proglove.Mark2SDK~1documentation~1ConnectSDK~1PGWearableApiErrorDomain\/fragments","op":"replace","value":[{"kind":"identifier","text":"PGWearableApiErrorDomain"}]},{"path":"\/references\/doc:~1~1com.proglove.Mark2SDK~1documentation~1ConnectSDK~1PGManager\/title","op":"replace","value":"PGManager"},{"op":"replace","value":[{"text":"PGManager","kind":"identifier"}],"path":"\/references\/doc:~1~1com.proglove.Mark2SDK~1documentation~1ConnectSDK~1PGManager\/fragments"},{"op":"replace","value":"PGConfigurationErrorDomain","path":"\/references\/doc:~1~1com.proglove.Mark2SDK~1documentation~1ConnectSDK~1PGConfigurationErrorDomain\/title"},{"op":"replace","path":"\/references\/doc:~1~1com.proglove.Mark2SDK~1documentation~1ConnectSDK~1PGConfigurationErrorDomain\/fragments","value":[{"text":"PGConfigurationErrorDomain","kind":"identifier"}]},{"path":"\/references\/doc:~1~1com.proglove.Mark2SDK~1documentation~1ConnectSDK~1PGDeviceInformationRequest\/title","value":"PGDeviceInformationRequest","op":"replace"},{"op":"replace","path":"\/references\/doc:~1~1com.proglove.Mark2SDK~1documentation~1ConnectSDK~1PGDeviceInformationRequest\/fragments","value":[{"text":"PGDeviceInformationRequest","kind":"identifier"}]},{"path":"\/references\/doc:~1~1com.proglove.Mark2SDK~1documentation~1ConnectSDK~1PGPeripheralDelegate\/title","value":"PGPeripheralDelegate","op":"replace"},{"value":[{"text":"PGPeripheralDelegate","kind":"identifier"}],"op":"replace","path":"\/references\/doc:~1~1com.proglove.Mark2SDK~1documentation~1ConnectSDK~1PGPeripheralDelegate\/fragments"},{"value":"PGMockPeripheral","path":"\/references\/doc:~1~1com.proglove.Mark2SDK~1documentation~1ConnectSDK~1PGMockPeripheral\/title","op":"replace"},{"op":"replace","path":"\/references\/doc:~1~1com.proglove.Mark2SDK~1documentation~1ConnectSDK~1PGMockPeripheral\/fragments","value":[{"text":"PGMockPeripheral","kind":"identifier"}]},{"op":"replace","path":"\/references\/doc:~1~1com.proglove.Mark2SDK~1documentation~1ConnectSDK~1PGSetDisplayOrientationRequest\/title","value":"PGSetDisplayOrientationRequest"},{"op":"replace","path":"\/references\/doc:~1~1com.proglove.Mark2SDK~1documentation~1ConnectSDK~1PGSetDisplayOrientationRequest\/fragments","value":[{"text":"PGSetDisplayOrientationRequest","kind":"identifier"}]},{"op":"replace","path":"\/references\/doc:~1~1com.proglove.Mark2SDK~1documentation~1ConnectSDK~1PGPeripheralErrorCentralHasRetriedConnectingKey\/title","value":"PGPeripheralErrorCentralHasRetriedConnectingKey"},{"path":"\/references\/doc:~1~1com.proglove.Mark2SDK~1documentation~1ConnectSDK~1PGPeripheralErrorCentralHasRetriedConnectingKey\/fragments","value":[{"kind":"identifier","text":"PGPeripheralErrorCentralHasRetriedConnectingKey"}],"op":"replace"},{"path":"\/references\/doc:~1~1com.proglove.Mark2SDK~1documentation~1ConnectSDK~1PGLogLevel\/title","value":"PGLogLevel","op":"replace"},{"path":"\/references\/doc:~1~1com.proglove.Mark2SDK~1documentation~1ConnectSDK~1PGLogLevel\/fragments","value":[{"text":"PGLogLevel","kind":"identifier"}],"op":"replace"},{"path":"\/references\/doc:~1~1com.proglove.Mark2SDK~1documentation~1ConnectSDK~1PGCloudErrorDomain\/title","value":"PGCloudErrorDomain","op":"replace"},{"op":"replace","path":"\/references\/doc:~1~1com.proglove.Mark2SDK~1documentation~1ConnectSDK~1PGCloudErrorDomain\/fragments","value":[{"text":"PGCloudErrorDomain","kind":"identifier"}]},{"path":"\/references\/doc:~1~1com.proglove.Mark2SDK~1documentation~1ConnectSDK~1PGPeripheral\/title","value":"PGPeripheral","op":"replace"},{"value":[{"kind":"identifier","text":"PGPeripheral"}],"path":"\/references\/doc:~1~1com.proglove.Mark2SDK~1documentation~1ConnectSDK~1PGPeripheral\/fragments","op":"replace"},{"value":"PGPeripheralErrorDomain","op":"replace","path":"\/references\/doc:~1~1com.proglove.Mark2SDK~1documentation~1ConnectSDK~1PGPeripheralErrorDomain\/title"},{"value":[{"kind":"identifier","text":"PGPeripheralErrorDomain"}],"path":"\/references\/doc:~1~1com.proglove.Mark2SDK~1documentation~1ConnectSDK~1PGPeripheralErrorDomain\/fragments","op":"replace"},{"path":"\/references\/doc:~1~1com.proglove.Mark2SDK~1documentation~1ConnectSDK~1PGPeripheralError\/title","op":"replace","value":"PGPeripheralError"},{"op":"replace","path":"\/references\/doc:~1~1com.proglove.Mark2SDK~1documentation~1ConnectSDK~1PGPeripheralError\/fragments","value":[{"text":"PGPeripheralError","kind":"identifier"}]},{"value":"PGImage","op":"replace","path":"\/references\/doc:~1~1com.proglove.Mark2SDK~1documentation~1ConnectSDK~1PGImage\/title"},{"path":"\/references\/doc:~1~1com.proglove.Mark2SDK~1documentation~1ConnectSDK~1PGImage\/fragments","op":"replace","value":[{"kind":"identifier","text":"PGImage"}]},{"value":"PGCentralManagerDelegate","op":"replace","path":"\/references\/doc:~1~1com.proglove.Mark2SDK~1documentation~1ConnectSDK~1PGCentralManagerDelegate\/title"},{"path":"\/references\/doc:~1~1com.proglove.Mark2SDK~1documentation~1ConnectSDK~1PGCentralManagerDelegate\/fragments","op":"replace","value":[{"text":"PGCentralManagerDelegate","kind":"identifier"}]},{"op":"replace","value":"PGCommandParams","path":"\/references\/doc:~1~1com.proglove.Mark2SDK~1documentation~1ConnectSDK~1PGCommandParams\/title"},{"op":"replace","path":"\/references\/doc:~1~1com.proglove.Mark2SDK~1documentation~1ConnectSDK~1PGCommandParams\/fragments","value":[{"kind":"identifier","text":"PGCommandParams"}]},{"op":"replace","value":"PGManagerState","path":"\/references\/doc:~1~1com.proglove.Mark2SDK~1documentation~1ConnectSDK~1PGManagerState\/title"},{"op":"replace","path":"\/references\/doc:~1~1com.proglove.Mark2SDK~1documentation~1ConnectSDK~1PGManagerState\/fragments","value":[{"kind":"identifier","text":"PGManagerState"}]},{"path":"\/references\/doc:~1~1com.proglove.Mark2SDK~1documentation~1ConnectSDK~1PGPairingQRGeneratorErrorCorrectionLevel\/title","value":"PGPairingQRGeneratorErrorCorrectionLevel","op":"replace"},{"value":[{"text":"PGPairingQRGeneratorErrorCorrectionLevel","kind":"identifier"}],"path":"\/references\/doc:~1~1com.proglove.Mark2SDK~1documentation~1ConnectSDK~1PGPairingQRGeneratorErrorCorrectionLevel\/fragments","op":"replace"},{"op":"replace","value":"PGDisplayApiErrorDomain","path":"\/references\/doc:~1~1com.proglove.Mark2SDK~1documentation~1ConnectSDK~1PGDisplayApiErrorDomain\/title"},{"op":"replace","value":[{"text":"PGDisplayApiErrorDomain","kind":"identifier"}],"path":"\/references\/doc:~1~1com.proglove.Mark2SDK~1documentation~1ConnectSDK~1PGDisplayApiErrorDomain\/fragments"},{"path":"\/references\/doc:~1~1com.proglove.Mark2SDK~1documentation~1ConnectSDK~1PGConfigurationApiError\/title","value":"PGConfigurationApiError","op":"replace"},{"op":"replace","path":"\/references\/doc:~1~1com.proglove.Mark2SDK~1documentation~1ConnectSDK~1PGConfigurationApiError\/fragments","value":[{"text":"PGConfigurationApiError","kind":"identifier"}]},{"value":"PGScreenData","op":"replace","path":"\/references\/doc:~1~1com.proglove.Mark2SDK~1documentation~1ConnectSDK~1PGScreenData\/title"},{"op":"replace","path":"\/references\/doc:~1~1com.proglove.Mark2SDK~1documentation~1ConnectSDK~1PGScreenData\/fragments","value":[{"kind":"identifier","text":"PGScreenData"}]},{"value":"PGPairingQRGeneratorOptions","path":"\/references\/doc:~1~1com.proglove.Mark2SDK~1documentation~1ConnectSDK~1PGPairingQRGeneratorOptions\/title","op":"replace"},{"path":"\/references\/doc:~1~1com.proglove.Mark2SDK~1documentation~1ConnectSDK~1PGPairingQRGeneratorOptions\/fragments","op":"replace","value":[{"text":"PGPairingQRGeneratorOptions","kind":"identifier"}]},{"op":"replace","path":"\/references\/doc:~1~1com.proglove.Mark2SDK~1documentation~1ConnectSDK~1PGCloudConnectionDelegate\/title","value":"PGCloudConnectionDelegate"},{"op":"replace","path":"\/references\/doc:~1~1com.proglove.Mark2SDK~1documentation~1ConnectSDK~1PGCloudConnectionDelegate\/fragments","value":[{"kind":"identifier","text":"PGCloudConnectionDelegate"}]},{"path":"\/references\/doc:~1~1com.proglove.Mark2SDK~1documentation~1ConnectSDK~1PGCaptureImageRequest\/title","value":"PGCaptureImageRequest","op":"replace"},{"value":[{"kind":"identifier","text":"PGCaptureImageRequest"}],"op":"replace","path":"\/references\/doc:~1~1com.proglove.Mark2SDK~1documentation~1ConnectSDK~1PGCaptureImageRequest\/fragments"},{"op":"replace","path":"\/references\/doc:~1~1com.proglove.Mark2SDK~1documentation~1ConnectSDK~1PGScannedBarcodeResult\/title","value":"PGScannedBarcodeResult"},{"op":"replace","value":[{"text":"PGScannedBarcodeResult","kind":"identifier"}],"path":"\/references\/doc:~1~1com.proglove.Mark2SDK~1documentation~1ConnectSDK~1PGScannedBarcodeResult\/fragments"}]}]}